{
  "appInfo" : {
    "build" : "213.5744.223",
    "buildDate" : "2021-11-27T07:14:41.296Z[UTC]",
    "productCode" : "IC",
    "generated" : "2021-12-30T09:19:53.41672Z",
    "os" : "Linux 5.11.0-41-generic",
    "runtime" : "JetBrains s.r.o. 11.0.13 11.0.13+7-b1751.19"
  },
  "runtimeInfo" : {
    "maxMemory" : 536870912,
    "numberOfProcessors" : 16,
    "maxNumberOfIndexingThreads" : 4,
    "maxSizeOfFileForIntelliSense" : 2560000,
    "maxSizeOfFileForContentLoading" : 20971520
  },
  "projectIndexingHistory" : {
    "projectName" : "plugins-layerfile",
    "times" : {
      "indexingReason" : "On project open",
      "totalUpdatingTime" : 4791321826,
      "indexingTime" : 63141000,
      "contentLoadingTime" : 2154384,
      "scanFilesTime" : 4646651000,
      "pushPropertiesTime" : 27000,
      "indexExtensionsTime" : 0,
      "updatingStart" : "2021-12-30T09:19:48.621358Z",
      "updatingEnd" : "2021-12-30T09:19:53.412709Z",
      "totalSuspendedTime" : 0,
      "wasInterrupted" : false
    },
    "fileCount" : {
      "numberOfFileProviders" : 15,
      "numberOfScannedFiles" : 217171,
      "numberOfFilesIndexedByInfrastructureExtensionsDuringScan" : 0,
      "numberOfFilesScheduledForIndexingAfterScan" : 1,
      "numberOfFilesIndexedByInfrastructureExtensionsDuringIndexingStage" : 0,
      "numberOfFilesIndexedWithLoadingContent" : 1
    },
    "totalStatsPerFileType" : [ {
      "fileType" : "textmate",
      "partOfTotalProcessingTime" : {
        "part" : 43539074,
        "total" : 43539074
      },
      "partOfTotalContentLoadingTime" : {
        "part" : 1835885,
        "total" : 1835885
      },
      "totalNumberOfFiles" : 1,
      "totalFilesSize" : 2763,
      "indexingSpeed" : {
        "totalBytes" : 2763,
        "totalTime" : 43539074
      },
      "biggestContributors" : [ {
        "providerName" : "Module 'plugins-layerfile' (plugins-layerfile)",
        "numberOfFiles" : 1,
        "totalFilesSize" : 2763,
        "partOfTotalProcessingTimeOfThisFileType" : {
          "part" : 43539074,
          "total" : 43539074
        }
      } ]
    } ],
    "totalStatsPerIndexer" : [ {
      "indexId" : "TodoIndex",
      "partOfTotalIndexingTime" : {
        "part" : 5652088,
        "total" : 12279607
      },
      "totalNumberOfFiles" : 1,
      "totalNumberOfFilesIndexedByExtensions" : 0,
      "totalFilesSize" : 2763,
      "indexingSpeed" : {
        "totalBytes" : 2763,
        "totalTime" : 5652088
      },
      "snapshotInputMappingStats" : {
        "totalRequests" : 0,
        "totalMisses" : 0,
        "totalHits" : 0
      }
    }, {
      "indexId" : "IdIndex",
      "partOfTotalIndexingTime" : {
        "part" : 4417010,
        "total" : 12279607
      },
      "totalNumberOfFiles" : 1,
      "totalNumberOfFilesIndexedByExtensions" : 0,
      "totalFilesSize" : 2763,
      "indexingSpeed" : {
        "totalBytes" : 2763,
        "totalTime" : 4417010
      },
      "snapshotInputMappingStats" : {
        "totalRequests" : 0,
        "totalMisses" : 0,
        "totalHits" : 0
      }
    }, {
      "indexId" : "Trigram.Index",
      "partOfTotalIndexingTime" : {
        "part" : 2203907,
        "total" : 12279607
      },
      "totalNumberOfFiles" : 1,
      "totalNumberOfFilesIndexedByExtensions" : 0,
      "totalFilesSize" : 2763,
      "indexingSpeed" : {
        "totalBytes" : 2763,
        "totalTime" : 2203907
      },
      "snapshotInputMappingStats" : {
        "totalRequests" : 0,
        "totalMisses" : 0,
        "totalHits" : 0
      }
    }, {
      "indexId" : "filetypes",
      "partOfTotalIndexingTime" : {
        "part" : 6602,
        "total" : 12279607
      },
      "totalNumberOfFiles" : 1,
      "totalNumberOfFilesIndexedByExtensions" : 0,
      "totalFilesSize" : 2763,
      "indexingSpeed" : {
        "totalBytes" : 2763,
        "totalTime" : 6602
      },
      "snapshotInputMappingStats" : {
        "totalRequests" : 0,
        "totalMisses" : 0,
        "totalHits" : 0
      }
    } ],
    "scanningStatistics" : [ {
      "providerName" : "Library Gradle: com.jetbrains:ideaIC:2021.3",
      "numberOfScannedFiles" : 99692,
      "numberOfSkippedFiles" : 89,
      "numberOfFilesForIndexing" : 0,
      "numberOfFilesFullyIndexedByInfrastructureExtensions" : 0,
      "scanningTime" : 2446266881,
      "timeProcessingUpToDateFiles" : 0,
      "timeUpdatingContentLessIndexes" : 85196638,
      "timeIndexingWithoutContent" : 0
    }, {
      "providerName" : "Library Gradle: com.jetbrains:ideaIC:2021.3",
      "numberOfScannedFiles" : 74296,
      "numberOfSkippedFiles" : 4,
      "numberOfFilesForIndexing" : 0,
      "numberOfFilesFullyIndexedByInfrastructureExtensions" : 0,
      "scanningTime" : 2183190869,
      "timeProcessingUpToDateFiles" : 0,
      "timeUpdatingContentLessIndexes" : 77873218,
      "timeIndexingWithoutContent" : 0
    }, {
      "providerName" : "JDK corretto-17",
      "numberOfScannedFiles" : 42130,
      "numberOfSkippedFiles" : 0,
      "numberOfFilesForIndexing" : 0,
      "numberOfFilesFullyIndexedByInfrastructureExtensions" : 0,
      "scanningTime" : 2007279774,
      "timeProcessingUpToDateFiles" : 0,
      "timeUpdatingContentLessIndexes" : 50538835,
      "timeIndexingWithoutContent" : 0
    }, {
      "providerName" : "Indexable set contributor 'com.intellij.javaee.ExternalResourcesRootsProvider@3d280cc6' (non-project)",
      "numberOfScannedFiles" : 224,
      "numberOfSkippedFiles" : 4,
      "numberOfFilesForIndexing" : 0,
      "numberOfFilesFullyIndexedByInfrastructureExtensions" : 0,
      "scanningTime" : 648070745,
      "timeProcessingUpToDateFiles" : 0,
      "timeUpdatingContentLessIndexes" : 1075841,
      "timeIndexingWithoutContent" : 0
    }, {
      "providerName" : "Library Gradle: junit:junit:4.13.2",
      "numberOfScannedFiles" : 578,
      "numberOfSkippedFiles" : 0,
      "numberOfFilesForIndexing" : 0,
      "numberOfFilesFullyIndexedByInfrastructureExtensions" : 0,
      "scanningTime" : 335013535,
      "timeProcessingUpToDateFiles" : 0,
      "timeUpdatingContentLessIndexes" : 12091105,
      "timeIndexingWithoutContent" : 0
    }, {
      "providerName" : "Library Gradle: org.jetbrains:annotations:22.0.0",
      "numberOfScannedFiles" : 86,
      "numberOfSkippedFiles" : 0,
      "numberOfFilesForIndexing" : 0,
      "numberOfFilesFullyIndexedByInfrastructureExtensions" : 0,
      "scanningTime" : 243061085,
      "timeProcessingUpToDateFiles" : 0,
      "timeUpdatingContentLessIndexes" : 1646376,
      "timeIndexingWithoutContent" : 0
    }, {
      "providerName" : "Library Gradle: org.hamcrest:hamcrest-core:1.3",
      "numberOfScannedFiles" : 88,
      "numberOfSkippedFiles" : 0,
      "numberOfFilesForIndexing" : 0,
      "numberOfFilesFullyIndexedByInfrastructureExtensions" : 0,
      "scanningTime" : 197802859,
      "timeProcessingUpToDateFiles" : 0,
      "timeUpdatingContentLessIndexes" : 2960254,
      "timeIndexingWithoutContent" : 0
    }, {
      "providerName" : "Module 'plugins-layerfile' (plugins-layerfile)",
      "numberOfScannedFiles" : 15,
      "numberOfSkippedFiles" : 0,
      "numberOfFilesForIndexing" : 1,
      "numberOfFilesFullyIndexedByInfrastructureExtensions" : 0,
      "scanningTime" : 137680530,
      "timeProcessingUpToDateFiles" : 0,
      "timeUpdatingContentLessIndexes" : 76624979,
      "timeIndexingWithoutContent" : 0
    }, {
      "providerName" : "Module 'plugins-layerfile.main' (main)",
      "numberOfScannedFiles" : 61,
      "numberOfSkippedFiles" : 0,
      "numberOfFilesForIndexing" : 0,
      "numberOfFilesFullyIndexedByInfrastructureExtensions" : 0,
      "scanningTime" : 121361382,
      "timeProcessingUpToDateFiles" : 0,
      "timeUpdatingContentLessIndexes" : 11288568,
      "timeIndexingWithoutContent" : 0
    }, {
      "providerName" : "Indexable set contributor 'Scratches & Consoles' (non-project)",
      "numberOfScannedFiles" : 1,
      "numberOfSkippedFiles" : 0,
      "numberOfFilesForIndexing" : 0,
      "numberOfFilesFullyIndexedByInfrastructureExtensions" : 0,
      "scanningTime" : 57504565,
      "timeProcessingUpToDateFiles" : 0,
      "timeUpdatingContentLessIndexes" : 23404,
      "timeIndexingWithoutContent" : 0
    }, {
      "providerName" : "Indexable set contributor 'Kotlin Script dependencies' (non-project)",
      "numberOfScannedFiles" : 0,
      "numberOfSkippedFiles" : 0,
      "numberOfFilesForIndexing" : 0,
      "numberOfFilesFullyIndexedByInfrastructureExtensions" : 0,
      "scanningTime" : 0,
      "timeProcessingUpToDateFiles" : 0,
      "timeUpdatingContentLessIndexes" : 0,
      "timeIndexingWithoutContent" : 0
    }, {
      "providerName" : "Indexable set contributor 'Scratches & Consoles' (project)",
      "numberOfScannedFiles" : 0,
      "numberOfSkippedFiles" : 0,
      "numberOfFilesForIndexing" : 0,
      "numberOfFilesFullyIndexedByInfrastructureExtensions" : 0,
      "scanningTime" : 0,
      "timeProcessingUpToDateFiles" : 0,
      "timeUpdatingContentLessIndexes" : 0,
      "timeIndexingWithoutContent" : 0
    }, {
      "providerName" : "Indexable set contributor 'com.intellij.javaee.ExternalResourcesRootsProvider@3d280cc6' (project)",
      "numberOfScannedFiles" : 0,
      "numberOfSkippedFiles" : 0,
      "numberOfFilesForIndexing" : 0,
      "numberOfFilesFullyIndexedByInfrastructureExtensions" : 0,
      "scanningTime" : 0,
      "timeProcessingUpToDateFiles" : 0,
      "timeUpdatingContentLessIndexes" : 0,
      "timeIndexingWithoutContent" : 0
    }, {
      "providerName" : "Module 'plugins-layerfile.test' (test)",
      "numberOfScannedFiles" : 0,
      "numberOfSkippedFiles" : 0,
      "numberOfFilesForIndexing" : 0,
      "numberOfFilesFullyIndexedByInfrastructureExtensions" : 0,
      "scanningTime" : 0,
      "timeProcessingUpToDateFiles" : 0,
      "timeUpdatingContentLessIndexes" : 0,
      "timeIndexingWithoutContent" : 0
    }, {
      "providerName" : "Indexable set contributor 'Kotlin Script dependencies' (project)",
      "numberOfScannedFiles" : 0,
      "numberOfSkippedFiles" : 0,
      "numberOfFilesForIndexing" : 0,
      "numberOfFilesFullyIndexedByInfrastructureExtensions" : 0,
      "scanningTime" : 0,
      "timeProcessingUpToDateFiles" : 0,
      "timeUpdatingContentLessIndexes" : 0,
      "timeIndexingWithoutContent" : 0
    } ],
    "fileProviderStatistics" : [ {
      "providerName" : "Module 'plugins-layerfile' (plugins-layerfile)",
      "totalNumberOfIndexedFiles" : 1,
      "totalNumberOfFilesFullyIndexedByExtensions" : 0,
      "totalIndexingTime" : 51092480,
      "contentLoadingTime" : 2154384,
      "numberOfTooLargeForIndexingFiles" : 0,
      "slowIndexedFiles" : [ ]
    } ]
  }
}