{
  "appInfo" : {
    "build" : "213.5744.223",
    "buildDate" : "2021-11-27T07:14:36.711Z[UTC]",
    "productCode" : "IC",
    "generated" : "2021-12-30T09:05:49.572601Z",
    "os" : "Linux 5.11.0-41-generic",
    "runtime" : "JetBrains s.r.o. 11.0.13 11.0.13+7-b1751.19"
  },
  "runtimeInfo" : {
    "maxMemory" : 536870912,
    "numberOfProcessors" : 16,
    "maxNumberOfIndexingThreads" : 4,
    "maxSizeOfFileForIntelliSense" : 2560000,
    "maxSizeOfFileForContentLoading" : 20971520
  },
  "projectIndexingHistory" : {
    "projectName" : "plugins-layerfile",
    "times" : {
      "indexingReason" : "Reindex requested by project root model changes",
      "totalUpdatingTime" : 374016603,
      "indexingTime" : 100184000,
      "contentLoadingTime" : 1452070,
      "scanFilesTime" : 223634000,
      "pushPropertiesTime" : 13000,
      "indexExtensionsTime" : 0,
      "updatingStart" : "2021-12-30T09:05:48.961613Z",
      "updatingEnd" : "2021-12-30T09:05:49.33563Z",
      "totalSuspendedTime" : 0,
      "wasInterrupted" : false
    },
    "fileCount" : {
      "numberOfFileProviders" : 15,
      "numberOfScannedFiles" : 220749,
      "numberOfFilesIndexedByInfrastructureExtensionsDuringScan" : 0,
      "numberOfFilesScheduledForIndexingAfterScan" : 2,
      "numberOfFilesIndexedByInfrastructureExtensionsDuringIndexingStage" : 0,
      "numberOfFilesIndexedWithLoadingContent" : 2
    },
    "totalStatsPerFileType" : [ {
      "fileType" : "JAVA",
      "partOfTotalProcessingTime" : {
        "part" : 99138447,
        "total" : 119304576
      },
      "partOfTotalContentLoadingTime" : {
        "part" : 1090226,
        "total" : 1740156
      },
      "totalNumberOfFiles" : 1,
      "totalFilesSize" : 25740,
      "indexingSpeed" : {
        "totalBytes" : 25740,
        "totalTime" : 99138447
      },
      "biggestContributors" : [ {
        "providerName" : "Module 'plugins-layerfile.main' (main)",
        "numberOfFiles" : 1,
        "totalFilesSize" : 25740,
        "partOfTotalProcessingTimeOfThisFileType" : {
          "part" : 99138447,
          "total" : 99138447
        }
      } ]
    }, {
      "fileType" : "PLAIN_TEXT",
      "partOfTotalProcessingTime" : {
        "part" : 20166129,
        "total" : 119304576
      },
      "partOfTotalContentLoadingTime" : {
        "part" : 649930,
        "total" : 1740156
      },
      "totalNumberOfFiles" : 1,
      "totalFilesSize" : 6632,
      "indexingSpeed" : {
        "totalBytes" : 6632,
        "totalTime" : 20166129
      },
      "biggestContributors" : [ {
        "providerName" : "Module 'plugins-layerfile.main' (main)",
        "numberOfFiles" : 1,
        "totalFilesSize" : 6632,
        "partOfTotalProcessingTimeOfThisFileType" : {
          "part" : 20166129,
          "total" : 20166129
        }
      } ]
    } ],
    "totalStatsPerIndexer" : [ {
      "indexId" : "Stubs",
      "partOfTotalIndexingTime" : {
        "part" : 52804497,
        "total" : 90725512
      },
      "totalNumberOfFiles" : 1,
      "totalNumberOfFilesIndexedByExtensions" : 0,
      "totalFilesSize" : 25740,
      "indexingSpeed" : {
        "totalBytes" : 25740,
        "totalTime" : 52804497
      },
      "snapshotInputMappingStats" : {
        "totalRequests" : 0,
        "totalMisses" : 0,
        "totalHits" : 0
      }
    }, {
      "indexId" : "TodoIndex",
      "partOfTotalIndexingTime" : {
        "part" : 13004708,
        "total" : 90725512
      },
      "totalNumberOfFiles" : 2,
      "totalNumberOfFilesIndexedByExtensions" : 0,
      "totalFilesSize" : 32372,
      "indexingSpeed" : {
        "totalBytes" : 32372,
        "totalTime" : 13004708
      },
      "snapshotInputMappingStats" : {
        "totalRequests" : 0,
        "totalMisses" : 0,
        "totalHits" : 0
      }
    }, {
      "indexId" : "Trigram.Index",
      "partOfTotalIndexingTime" : {
        "part" : 8351455,
        "total" : 90725512
      },
      "totalNumberOfFiles" : 2,
      "totalNumberOfFilesIndexedByExtensions" : 0,
      "totalFilesSize" : 32372,
      "indexingSpeed" : {
        "totalBytes" : 32372,
        "totalTime" : 8351455
      },
      "snapshotInputMappingStats" : {
        "totalRequests" : 0,
        "totalMisses" : 0,
        "totalHits" : 0
      }
    }, {
      "indexId" : "java.fun.expression",
      "partOfTotalIndexingTime" : {
        "part" : 5297062,
        "total" : 90725512
      },
      "totalNumberOfFiles" : 1,
      "totalNumberOfFilesIndexedByExtensions" : 0,
      "totalFilesSize" : 25740,
      "indexingSpeed" : {
        "totalBytes" : 25740,
        "totalTime" : 5297062
      },
      "snapshotInputMappingStats" : {
        "totalRequests" : 0,
        "totalMisses" : 0,
        "totalHits" : 0
      }
    }, {
      "indexId" : "java.null.method.argument",
      "partOfTotalIndexingTime" : {
        "part" : 4810389,
        "total" : 90725512
      },
      "totalNumberOfFiles" : 1,
      "totalNumberOfFilesIndexedByExtensions" : 0,
      "totalFilesSize" : 25740,
      "indexingSpeed" : {
        "totalBytes" : 25740,
        "totalTime" : 4810389
      },
      "snapshotInputMappingStats" : {
        "totalRequests" : 0,
        "totalMisses" : 0,
        "totalHits" : 0
      }
    }, {
      "indexId" : "IdIndex",
      "partOfTotalIndexingTime" : {
        "part" : 4594364,
        "total" : 90725512
      },
      "totalNumberOfFiles" : 2,
      "totalNumberOfFilesIndexedByExtensions" : 0,
      "totalFilesSize" : 32372,
      "indexingSpeed" : {
        "totalBytes" : 32372,
        "totalTime" : 4594364
      },
      "snapshotInputMappingStats" : {
        "totalRequests" : 0,
        "totalMisses" : 0,
        "totalHits" : 0
      }
    }, {
      "indexId" : "java.binary.plus.expression",
      "partOfTotalIndexingTime" : {
        "part" : 1863037,
        "total" : 90725512
      },
      "totalNumberOfFiles" : 1,
      "totalNumberOfFilesIndexedByExtensions" : 0,
      "totalFilesSize" : 25740,
      "indexingSpeed" : {
        "totalBytes" : 25740,
        "totalTime" : 1863037
      },
      "snapshotInputMappingStats" : {
        "totalRequests" : 0,
        "totalMisses" : 0,
        "totalHits" : 0
      }
    } ],
    "scanningStatistics" : [ {
      "providerName" : "Indexable set contributor 'Kotlin Script dependencies' (project)",
      "numberOfScannedFiles" : 3578,
      "numberOfSkippedFiles" : 0,
      "numberOfFilesForIndexing" : 0,
      "numberOfFilesFullyIndexedByInfrastructureExtensions" : 0,
      "scanningTime" : 115892709,
      "timeProcessingUpToDateFiles" : 0,
      "timeUpdatingContentLessIndexes" : 4774544,
      "timeIndexingWithoutContent" : 0
    }, {
      "providerName" : "Library Gradle: com.jetbrains:ideaIC:2021.3",
      "numberOfScannedFiles" : 74296,
      "numberOfSkippedFiles" : 4,
      "numberOfFilesForIndexing" : 0,
      "numberOfFilesFullyIndexedByInfrastructureExtensions" : 0,
      "scanningTime" : 74947337,
      "timeProcessingUpToDateFiles" : 0,
      "timeUpdatingContentLessIndexes" : 0,
      "timeIndexingWithoutContent" : 0
    }, {
      "providerName" : "Library Gradle: com.jetbrains:ideaIC:2021.3",
      "numberOfScannedFiles" : 99692,
      "numberOfSkippedFiles" : 89,
      "numberOfFilesForIndexing" : 0,
      "numberOfFilesFullyIndexedByInfrastructureExtensions" : 0,
      "scanningTime" : 67996344,
      "timeProcessingUpToDateFiles" : 0,
      "timeUpdatingContentLessIndexes" : 0,
      "timeIndexingWithoutContent" : 0
    }, {
      "providerName" : "JDK corretto-17",
      "numberOfScannedFiles" : 42130,
      "numberOfSkippedFiles" : 0,
      "numberOfFilesForIndexing" : 0,
      "numberOfFilesFullyIndexedByInfrastructureExtensions" : 0,
      "scanningTime" : 51818625,
      "timeProcessingUpToDateFiles" : 0,
      "timeUpdatingContentLessIndexes" : 0,
      "timeIndexingWithoutContent" : 0
    }, {
      "providerName" : "Library Gradle: junit:junit:4.13.2",
      "numberOfScannedFiles" : 578,
      "numberOfSkippedFiles" : 0,
      "numberOfFilesForIndexing" : 0,
      "numberOfFilesFullyIndexedByInfrastructureExtensions" : 0,
      "scanningTime" : 2062338,
      "timeProcessingUpToDateFiles" : 0,
      "timeUpdatingContentLessIndexes" : 0,
      "timeIndexingWithoutContent" : 0
    }, {
      "providerName" : "Indexable set contributor 'com.intellij.javaee.ExternalResourcesRootsProvider@3ff6af25' (non-project)",
      "numberOfScannedFiles" : 224,
      "numberOfSkippedFiles" : 4,
      "numberOfFilesForIndexing" : 0,
      "numberOfFilesFullyIndexedByInfrastructureExtensions" : 0,
      "scanningTime" : 696338,
      "timeProcessingUpToDateFiles" : 0,
      "timeUpdatingContentLessIndexes" : 0,
      "timeIndexingWithoutContent" : 0
    }, {
      "providerName" : "Module 'plugins-layerfile.main' (main)",
      "numberOfScannedFiles" : 61,
      "numberOfSkippedFiles" : 0,
      "numberOfFilesForIndexing" : 2,
      "numberOfFilesFullyIndexedByInfrastructureExtensions" : 0,
      "scanningTime" : 405913,
      "timeProcessingUpToDateFiles" : 0,
      "timeUpdatingContentLessIndexes" : 11151,
      "timeIndexingWithoutContent" : 50456
    }, {
      "providerName" : "Library Gradle: org.hamcrest:hamcrest-core:1.3",
      "numberOfScannedFiles" : 88,
      "numberOfSkippedFiles" : 0,
      "numberOfFilesForIndexing" : 0,
      "numberOfFilesFullyIndexedByInfrastructureExtensions" : 0,
      "scanningTime" : 275866,
      "timeProcessingUpToDateFiles" : 0,
      "timeUpdatingContentLessIndexes" : 0,
      "timeIndexingWithoutContent" : 0
    }, {
      "providerName" : "Library Gradle: org.jetbrains:annotations:22.0.0",
      "numberOfScannedFiles" : 86,
      "numberOfSkippedFiles" : 0,
      "numberOfFilesForIndexing" : 0,
      "numberOfFilesFullyIndexedByInfrastructureExtensions" : 0,
      "scanningTime" : 161349,
      "timeProcessingUpToDateFiles" : 0,
      "timeUpdatingContentLessIndexes" : 0,
      "timeIndexingWithoutContent" : 0
    }, {
      "providerName" : "Module 'plugins-layerfile' (plugins-layerfile)",
      "numberOfScannedFiles" : 15,
      "numberOfSkippedFiles" : 0,
      "numberOfFilesForIndexing" : 0,
      "numberOfFilesFullyIndexedByInfrastructureExtensions" : 0,
      "scanningTime" : 65250,
      "timeProcessingUpToDateFiles" : 0,
      "timeUpdatingContentLessIndexes" : 0,
      "timeIndexingWithoutContent" : 0
    }, {
      "providerName" : "Indexable set contributor 'Scratches & Consoles' (non-project)",
      "numberOfScannedFiles" : 1,
      "numberOfSkippedFiles" : 0,
      "numberOfFilesForIndexing" : 0,
      "numberOfFilesFullyIndexedByInfrastructureExtensions" : 0,
      "scanningTime" : 1954,
      "timeProcessingUpToDateFiles" : 0,
      "timeUpdatingContentLessIndexes" : 0,
      "timeIndexingWithoutContent" : 0
    }, {
      "providerName" : "Indexable set contributor 'com.intellij.javaee.ExternalResourcesRootsProvider@3ff6af25' (project)",
      "numberOfScannedFiles" : 0,
      "numberOfSkippedFiles" : 0,
      "numberOfFilesForIndexing" : 0,
      "numberOfFilesFullyIndexedByInfrastructureExtensions" : 0,
      "scanningTime" : 0,
      "timeProcessingUpToDateFiles" : 0,
      "timeUpdatingContentLessIndexes" : 0,
      "timeIndexingWithoutContent" : 0
    }, {
      "providerName" : "Indexable set contributor 'Scratches & Consoles' (project)",
      "numberOfScannedFiles" : 0,
      "numberOfSkippedFiles" : 0,
      "numberOfFilesForIndexing" : 0,
      "numberOfFilesFullyIndexedByInfrastructureExtensions" : 0,
      "scanningTime" : 0,
      "timeProcessingUpToDateFiles" : 0,
      "timeUpdatingContentLessIndexes" : 0,
      "timeIndexingWithoutContent" : 0
    }, {
      "providerName" : "Indexable set contributor 'Kotlin Script dependencies' (non-project)",
      "numberOfScannedFiles" : 0,
      "numberOfSkippedFiles" : 0,
      "numberOfFilesForIndexing" : 0,
      "numberOfFilesFullyIndexedByInfrastructureExtensions" : 0,
      "scanningTime" : 0,
      "timeProcessingUpToDateFiles" : 0,
      "timeUpdatingContentLessIndexes" : 0,
      "timeIndexingWithoutContent" : 0
    }, {
      "providerName" : "Module 'plugins-layerfile.test' (test)",
      "numberOfScannedFiles" : 0,
      "numberOfSkippedFiles" : 0,
      "numberOfFilesForIndexing" : 0,
      "numberOfFilesFullyIndexedByInfrastructureExtensions" : 0,
      "scanningTime" : 0,
      "timeProcessingUpToDateFiles" : 0,
      "timeUpdatingContentLessIndexes" : 0,
      "timeIndexingWithoutContent" : 0
    } ],
    "fileProviderStatistics" : [ {
      "providerName" : "Module 'plugins-layerfile.main' (main)",
      "totalNumberOfIndexedFiles" : 2,
      "totalNumberOfFilesFullyIndexedByExtensions" : 0,
      "totalIndexingTime" : 99553507,
      "contentLoadingTime" : 1452070,
      "numberOfTooLargeForIndexingFiles" : 0,
      "slowIndexedFiles" : [ ]
    } ]
  }
}