{
  "appInfo" : {
    "build" : "213.5744.223",
    "buildDate" : "2021-11-27T07:14:26.297Z[UTC]",
    "productCode" : "IC",
    "generated" : "2021-12-28T11:06:38.194847Z",
    "os" : "Linux 5.11.0-41-generic",
    "runtime" : "JetBrains s.r.o. 11.0.13 11.0.13+7-b1751.19"
  },
  "runtimeInfo" : {
    "maxMemory" : 536870912,
    "numberOfProcessors" : 16,
    "maxNumberOfIndexingThreads" : 4,
    "maxSizeOfFileForIntelliSense" : 2560000,
    "maxSizeOfFileForContentLoading" : 20971520
  },
  "projectIndexingHistory" : {
    "projectName" : "plugins-layerfile",
    "times" : {
      "indexingReason" : "On project open",
      "totalUpdatingTime" : 4673600917,
      "indexingTime" : 141658000,
      "contentLoadingTime" : 4000196,
      "scanFilesTime" : 4447827000,
      "pushPropertiesTime" : 40000,
      "indexExtensionsTime" : 0,
      "updatingStart" : "2021-12-28T11:06:33.517041Z",
      "updatingEnd" : "2021-12-28T11:06:38.190675Z",
      "totalSuspendedTime" : 0,
      "wasInterrupted" : false
    },
    "fileCount" : {
      "numberOfFileProviders" : 15,
      "numberOfScannedFiles" : 217169,
      "numberOfFilesIndexedByInfrastructureExtensionsDuringScan" : 0,
      "numberOfFilesScheduledForIndexingAfterScan" : 2,
      "numberOfFilesIndexedByInfrastructureExtensionsDuringIndexingStage" : 0,
      "numberOfFilesIndexedWithLoadingContent" : 2
    },
    "totalStatsPerFileType" : [ {
      "fileType" : "Layerfile",
      "partOfTotalProcessingTime" : {
        "part" : 122407994,
        "total" : 160077256
      },
      "partOfTotalContentLoadingTime" : {
        "part" : 1742041,
        "total" : 5035075
      },
      "totalNumberOfFiles" : 1,
      "totalFilesSize" : 996,
      "indexingSpeed" : {
        "totalBytes" : 996,
        "totalTime" : 122407994
      },
      "biggestContributors" : [ {
        "providerName" : "Module 'plugins-layerfile' (plugins-layerfile)",
        "numberOfFiles" : 1,
        "totalFilesSize" : 996,
        "partOfTotalProcessingTimeOfThisFileType" : {
          "part" : 122407994,
          "total" : 122407994
        }
      } ]
    }, {
      "fileType" : "textmate",
      "partOfTotalProcessingTime" : {
        "part" : 37669262,
        "total" : 160077256
      },
      "partOfTotalContentLoadingTime" : {
        "part" : 3293034,
        "total" : 5035075
      },
      "totalNumberOfFiles" : 1,
      "totalFilesSize" : 2763,
      "indexingSpeed" : {
        "totalBytes" : 2763,
        "totalTime" : 37669262
      },
      "biggestContributors" : [ {
        "providerName" : "Module 'plugins-layerfile' (plugins-layerfile)",
        "numberOfFiles" : 1,
        "totalFilesSize" : 2763,
        "partOfTotalProcessingTimeOfThisFileType" : {
          "part" : 37669262,
          "total" : 37669262
        }
      } ]
    } ],
    "totalStatsPerIndexer" : [ {
      "indexId" : "TodoIndex",
      "partOfTotalIndexingTime" : {
        "part" : 13413556,
        "total" : 19585195
      },
      "totalNumberOfFiles" : 2,
      "totalNumberOfFilesIndexedByExtensions" : 0,
      "totalFilesSize" : 3759,
      "indexingSpeed" : {
        "totalBytes" : 3759,
        "totalTime" : 13413556
      },
      "snapshotInputMappingStats" : {
        "totalRequests" : 0,
        "totalMisses" : 0,
        "totalHits" : 0
      }
    }, {
      "indexId" : "IdIndex",
      "partOfTotalIndexingTime" : {
        "part" : 3811237,
        "total" : 19585195
      },
      "totalNumberOfFiles" : 1,
      "totalNumberOfFilesIndexedByExtensions" : 0,
      "totalFilesSize" : 2763,
      "indexingSpeed" : {
        "totalBytes" : 2763,
        "totalTime" : 3811237
      },
      "snapshotInputMappingStats" : {
        "totalRequests" : 0,
        "totalMisses" : 0,
        "totalHits" : 0
      }
    }, {
      "indexId" : "Trigram.Index",
      "partOfTotalIndexingTime" : {
        "part" : 2348680,
        "total" : 19585195
      },
      "totalNumberOfFiles" : 1,
      "totalNumberOfFilesIndexedByExtensions" : 0,
      "totalFilesSize" : 2763,
      "indexingSpeed" : {
        "totalBytes" : 2763,
        "totalTime" : 2348680
      },
      "snapshotInputMappingStats" : {
        "totalRequests" : 0,
        "totalMisses" : 0,
        "totalHits" : 0
      }
    }, {
      "indexId" : "filetypes",
      "partOfTotalIndexingTime" : {
        "part" : 11722,
        "total" : 19585195
      },
      "totalNumberOfFiles" : 1,
      "totalNumberOfFilesIndexedByExtensions" : 0,
      "totalFilesSize" : 2763,
      "indexingSpeed" : {
        "totalBytes" : 2763,
        "totalTime" : 11722
      },
      "snapshotInputMappingStats" : {
        "totalRequests" : 0,
        "totalMisses" : 0,
        "totalHits" : 0
      }
    } ],
    "scanningStatistics" : [ {
      "providerName" : "Library Gradle: com.jetbrains:ideaIC:2021.3",
      "numberOfScannedFiles" : 100631,
      "numberOfSkippedFiles" : 89,
      "numberOfFilesForIndexing" : 0,
      "numberOfFilesFullyIndexedByInfrastructureExtensions" : 0,
      "scanningTime" : 2472032982,
      "timeProcessingUpToDateFiles" : 0,
      "timeUpdatingContentLessIndexes" : 94925161,
      "timeIndexingWithoutContent" : 0
    }, {
      "providerName" : "Library Gradle: com.jetbrains:ideaIC:2021.3",
      "numberOfScannedFiles" : 73357,
      "numberOfSkippedFiles" : 4,
      "numberOfFilesForIndexing" : 0,
      "numberOfFilesFullyIndexedByInfrastructureExtensions" : 0,
      "scanningTime" : 2406422372,
      "timeProcessingUpToDateFiles" : 0,
      "timeUpdatingContentLessIndexes" : 82361103,
      "timeIndexingWithoutContent" : 0
    }, {
      "providerName" : "JDK corretto-17",
      "numberOfScannedFiles" : 42130,
      "numberOfSkippedFiles" : 0,
      "numberOfFilesForIndexing" : 0,
      "numberOfFilesFullyIndexedByInfrastructureExtensions" : 0,
      "scanningTime" : 2141488644,
      "timeProcessingUpToDateFiles" : 0,
      "timeUpdatingContentLessIndexes" : 76780061,
      "timeIndexingWithoutContent" : 0
    }, {
      "providerName" : "Indexable set contributor 'com.intellij.javaee.ExternalResourcesRootsProvider@51840018' (non-project)",
      "numberOfScannedFiles" : 224,
      "numberOfSkippedFiles" : 4,
      "numberOfFilesForIndexing" : 0,
      "numberOfFilesFullyIndexedByInfrastructureExtensions" : 0,
      "scanningTime" : 479511785,
      "timeProcessingUpToDateFiles" : 0,
      "timeUpdatingContentLessIndexes" : 8278822,
      "timeIndexingWithoutContent" : 0
    }, {
      "providerName" : "Library Gradle: junit:junit:4.13.2",
      "numberOfScannedFiles" : 578,
      "numberOfSkippedFiles" : 0,
      "numberOfFilesForIndexing" : 0,
      "numberOfFilesFullyIndexedByInfrastructureExtensions" : 0,
      "scanningTime" : 237018382,
      "timeProcessingUpToDateFiles" : 0,
      "timeUpdatingContentLessIndexes" : 16192718,
      "timeIndexingWithoutContent" : 0
    }, {
      "providerName" : "Library Gradle: org.jetbrains:annotations:22.0.0",
      "numberOfScannedFiles" : 86,
      "numberOfSkippedFiles" : 0,
      "numberOfFilesForIndexing" : 0,
      "numberOfFilesFullyIndexedByInfrastructureExtensions" : 0,
      "scanningTime" : 117600808,
      "timeProcessingUpToDateFiles" : 0,
      "timeUpdatingContentLessIndexes" : 5783387,
      "timeIndexingWithoutContent" : 0
    }, {
      "providerName" : "Library Gradle: org.hamcrest:hamcrest-core:1.3",
      "numberOfScannedFiles" : 88,
      "numberOfSkippedFiles" : 0,
      "numberOfFilesForIndexing" : 0,
      "numberOfFilesFullyIndexedByInfrastructureExtensions" : 0,
      "scanningTime" : 105524246,
      "timeProcessingUpToDateFiles" : 0,
      "timeUpdatingContentLessIndexes" : 6964096,
      "timeIndexingWithoutContent" : 0
    }, {
      "providerName" : "Module 'plugins-layerfile' (plugins-layerfile)",
      "numberOfScannedFiles" : 15,
      "numberOfSkippedFiles" : 0,
      "numberOfFilesForIndexing" : 2,
      "numberOfFilesFullyIndexedByInfrastructureExtensions" : 0,
      "scanningTime" : 95858810,
      "timeProcessingUpToDateFiles" : 0,
      "timeUpdatingContentLessIndexes" : 47263515,
      "timeIndexingWithoutContent" : 1795952
    }, {
      "providerName" : "Module 'plugins-layerfile.main' (main)",
      "numberOfScannedFiles" : 59,
      "numberOfSkippedFiles" : 0,
      "numberOfFilesForIndexing" : 0,
      "numberOfFilesFullyIndexedByInfrastructureExtensions" : 0,
      "scanningTime" : 81715502,
      "timeProcessingUpToDateFiles" : 0,
      "timeUpdatingContentLessIndexes" : 1533036,
      "timeIndexingWithoutContent" : 0
    }, {
      "providerName" : "Indexable set contributor 'Scratches & Consoles' (non-project)",
      "numberOfScannedFiles" : 1,
      "numberOfSkippedFiles" : 0,
      "numberOfFilesForIndexing" : 0,
      "numberOfFilesFullyIndexedByInfrastructureExtensions" : 0,
      "scanningTime" : 53743714,
      "timeProcessingUpToDateFiles" : 0,
      "timeUpdatingContentLessIndexes" : 25508,
      "timeIndexingWithoutContent" : 0
    }, {
      "providerName" : "Indexable set contributor 'Kotlin Script dependencies' (non-project)",
      "numberOfScannedFiles" : 0,
      "numberOfSkippedFiles" : 0,
      "numberOfFilesForIndexing" : 0,
      "numberOfFilesFullyIndexedByInfrastructureExtensions" : 0,
      "scanningTime" : 0,
      "timeProcessingUpToDateFiles" : 0,
      "timeUpdatingContentLessIndexes" : 0,
      "timeIndexingWithoutContent" : 0
    }, {
      "providerName" : "Indexable set contributor 'Scratches & Consoles' (project)",
      "numberOfScannedFiles" : 0,
      "numberOfSkippedFiles" : 0,
      "numberOfFilesForIndexing" : 0,
      "numberOfFilesFullyIndexedByInfrastructureExtensions" : 0,
      "scanningTime" : 0,
      "timeProcessingUpToDateFiles" : 0,
      "timeUpdatingContentLessIndexes" : 0,
      "timeIndexingWithoutContent" : 0
    }, {
      "providerName" : "Indexable set contributor 'com.intellij.javaee.ExternalResourcesRootsProvider@51840018' (project)",
      "numberOfScannedFiles" : 0,
      "numberOfSkippedFiles" : 0,
      "numberOfFilesForIndexing" : 0,
      "numberOfFilesFullyIndexedByInfrastructureExtensions" : 0,
      "scanningTime" : 0,
      "timeProcessingUpToDateFiles" : 0,
      "timeUpdatingContentLessIndexes" : 0,
      "timeIndexingWithoutContent" : 0
    }, {
      "providerName" : "Module 'plugins-layerfile.test' (test)",
      "numberOfScannedFiles" : 0,
      "numberOfSkippedFiles" : 0,
      "numberOfFilesForIndexing" : 0,
      "numberOfFilesFullyIndexedByInfrastructureExtensions" : 0,
      "scanningTime" : 0,
      "timeProcessingUpToDateFiles" : 0,
      "timeUpdatingContentLessIndexes" : 0,
      "timeIndexingWithoutContent" : 0
    }, {
      "providerName" : "Indexable set contributor 'Kotlin Script dependencies' (project)",
      "numberOfScannedFiles" : 0,
      "numberOfSkippedFiles" : 0,
      "numberOfFilesForIndexing" : 0,
      "numberOfFilesFullyIndexedByInfrastructureExtensions" : 0,
      "scanningTime" : 0,
      "timeProcessingUpToDateFiles" : 0,
      "timeUpdatingContentLessIndexes" : 0,
      "timeIndexingWithoutContent" : 0
    } ],
    "fileProviderStatistics" : [ {
      "providerName" : "Module 'plugins-layerfile' (plugins-layerfile)",
      "totalNumberOfIndexedFiles" : 2,
      "totalNumberOfFilesFullyIndexedByExtensions" : 0,
      "totalIndexingTime" : 127175967,
      "contentLoadingTime" : 4000196,
      "numberOfTooLargeForIndexingFiles" : 0,
      "slowIndexedFiles" : [ ]
    } ]
  }
}